mpegCoder-3.2.4.data/purelib/mpegCoder/__init__.py
mpegCoder-3.2.4.data/purelib/mpegCoder/webtools.py
mpegCoder-3.2.4.dist-info/LICENSE
mpegCoder-3.2.4.dist-info/METADATA
mpegCoder-3.2.4.dist-info/WHEEL
mpegCoder-3.2.4.dist-info/top_level.txt
mpegCoder-3.2.4.dist-info/RECORD
