Metadata-Version: 2.1
Name: mpegCoder
Version: 3.2.4
Summary: A FFmpeg module which could provide a class for encoding, decoding, or streaming a video in any format.
Home-page: https://github.com/cainmagi/FFmpeg-Encoder-Decoder-for-Python
Author: Yuchen Jin
Author-email: cainmagi@gmail.com
License: GPLv3
Project-URL: Tracker, https://github.com/cainmagi/FFmpeg-Encoder-Decoder-for-Python/issues
Project-URL: Documentation, https://cainmagi.github.io/FFmpeg-Encoder-Decoder-for-Python/
Keywords: python,h264,video,rtsp,ffmpeg,rtmp,encoder,numpy,python3,python3-library,ffmpeg-wrapper,video-stream,python-c-api,rtsp-push,rtmp-push,rtsp-player,rtmp-player,ffmpeg-encoder
Platform: linux-x86_64
Classifier: Intended Audience :: Developers
Classifier: Programming Language :: Python :: 3
Classifier: Programming Language :: Python :: 3 :: Only
Classifier: Programming Language :: Python :: 3.10
Classifier: Programming Language :: Python :: 3.9
Classifier: Programming Language :: Python :: 3.8
Classifier: Programming Language :: Python :: 3.7
Classifier: Programming Language :: Python :: 3.6
Classifier: License :: OSI Approved :: GNU General Public License v3 (GPLv3)
Classifier: Operating System :: POSIX :: Linux
Classifier: Operating System :: Microsoft :: Windows
Classifier: Topic :: Software Development :: Libraries :: Python Modules
Classifier: Topic :: Multimedia :: Video
Classifier: Topic :: Multimedia :: Video :: Conversion
Classifier: Topic :: Multimedia :: Video :: Display
Classifier: Topic :: Scientific/Engineering
Requires-Python: >=3.6,<3.11
License-File: LICENSE
Requires-Dist: urllib3 (>=1.26.0)
Requires-Dist: numpy (>=1.16.0) ; python_version < "3.7.0"
Requires-Dist: numpy (>=1.20.0) ; python_version >= "3.7.0" and python_version < "3.8.0"
Requires-Dist: numpy (>=1.22.0) ; python_version >= "3.8.0"
